{
    "widgets": {
        "navBar": {
            "path": {
                "main": "Главная",
                "alerts": "Оповещения",
                "forecast": "Новый прогноз",
                "dbConnections": "Подключения к БД",
                "aiAgent": "ИИ Агент"
            },
            "title": "HorizonTSD",
            "toggleTooltip": {
                "collapse": "Свернуть боковую панель",
                "expand": "Развернуть боковую панель"
            }
        },
        "comingSoon": "Скоро появится",
        "weatherData": "Погодные данные",
        "weatherStatCard": {
            "loading": "Загрузка...",
            "errorLoadingChartsData": "Ошибка загрузки данных графиков",
            "titleTemperature": "Температура",
            "titleWindSpeed": "Скорость ветра",
            "titleHumidity": "Влажность",
            "titlePressure": "Давление",
            "descriptionLast24h": "Последние 24 часа",
            "trendPositive": "↑",
            "trendNegative": "↓"
        },
        "LoadForecastGraphBlock": {
            "title": "Прогноз",
            "sensorsLoading": "Загрузка...",
            "sensorsError": "Ошибка загрузки датчиков!",
            "dataLoading": "Загрузка данных...",
            "errorPrefix": "Ошибка: ",
            "unknownError": "Неизвестная ошибка",
            "navbar": {
                "disabledOptionsLabel": "Отключенные опции",
                "timeRangeOptions": {
                    "option1": "сейчас-1д до сейчас+1д",
                    "yesterday": "вчера",
                    "tommorow": "завтра"
                },
                "fromLabel": "с:",
                "toLabel": "по:",
                "absoluteTimeRangeHeading": "Абсолютный временной диапазон",
                "applyTimeRangeButton": "Применить временной диапазон",
                "timeUnits": {
                    "minute": "минута",
                    "hour": "час",
                    "day": "день"
                },
                "lastTimeUnit": "Последние: {{count}} {{unit}}",
                "timezoneCaption": "Всемирное координированное время UTC, GMT UTC+00:00",
                "timezoneLabel": "часовой пояс:",
                "selectPeriodPlaceholder": "Выберите период",
                "sensorLabel": "источник данных",
                "selectSensorPlaceholder": "Выберите датчик",
                "refreshAtLabel": "частота обновления"
            }
        },
        "Metrix": {
            "data": "Таблица метрик по точкам",
            "selectDataRange": "Выберите диапазон данных",
            "sensorSelection": "Выбор датчика",
            "modelSelection": "Выбор модели",
            "startDate": "Дата начала",
            "endDate": "Дата окончания",
            "dateRange": "Диапазон дат",
            "title": "Метрики модели за выбранный период",
            "choseAlert": "Выберите диапазон дат для отображения метрик прогноза"
        },
        "GridDetails": {
            "tableTitle": "Таблица",
            "sensorSelectionLabel": "Выбор датчика",
            "modelSelectionLabel": "Выбор модели",
            "dateTimeHeader": "Дата и время",
            "sensorFetchError": "Ошибка получения датчиков",
            "forecastFetchErrorPrefix": "Ошибка получения прогноза:",
            "loadingMessage": "Загрузка..."
        },
        "metrixBloc": {
            "error1": "Ошибка загрузки данных:",
            "mae": "Средняя абсолютная ошибка (MAE)",
            "rmse": "Среднеквадратичная ошибка (RMSE)",
            "r2": "Коэффициент детерминации (R²)",
            "mape": "Средняя абсолютная процентная ошибка (MAPE)"
        },
        "alertsContent": {
            "alertRules": "Правила оповещений",
            "search": "Поиск",
            "searchAlertsPlaceholder": "поиск оповещений",
            "createButton": "Создать",
            "errorCreatingAlert": "Ошибка создания оповещения:",
            "errorDeletingAlert": "Ошибка удаления оповещения:",
            "sensorSelection": "Выбор датчика",
            "modelSelection": "Выбор модели",
            "alertBlockName": "название",
            "alertBlockTriggerFrequency": "частота срабатывания",
            "alertBlockMessage": "сообщение",
            "alertBlockStartDate": "дата начала",
            "alertBlockEndDate": "дата окончания",
            "alertBlockStartWarningInterval": "начало интервала предупреждения",
            "alertBlockSensorId": "идентификатор датчика",
            "alertBlockModel": "модель",
            "alertBlockThresholdValue": "пороговое значение",
            "alertBlockScheme": "схема",
            "alertBlockTelegram": "telegram",
            "alertBlockEmail": "email",
            "alertBlockIncludeGraph": "включить график",
            "alertBlockActions": "Действия",
            "alertBlockViewButton": "просмотр",
            "alertBlockMoreButton": "Ещё",
            "alertBlockEditMenuItem": "Редактировать",
            "alertBlockDeleteMenuItem": "Удалить",
            "createAlertModalTitleEdit": "Редактировать оповещение",
            "createAlertModalTitleCreate": "Создать оповещение",
            "createAlertModalAlertNameLabel": "Название оповещения*",
            "createAlertModalSensorLabel": "Датчик*",
            "createAlertModalModelLabel": "Модель*",
            "createAlertModalThresholdValueLabel": "Пороговое значение",
            "createAlertModalAlertSchemeLabel": "Схема оповещения",
            "createAlertModalAlertSchemeAboveValue": "Выше значения",
            "createAlertModalAlertSchemeBelowValue": "Ниже значения",
            "createAlertModalTriggerFrequencyLabel": "Частота срабатывания",
            "createAlertModalStartDateLabel": "Дата начала",
            "createAlertModalStartTimeLabel": "Время начала",
            "createAlertModalEndDateLabel": "Дата окончания",
            "createAlertModalEndTimeLabel": "Время окончания",
            "createAlertModalEmailAddressesLabel": "Email адреса",
            "createAlertModalEmailAddressesPlaceholder": "email1@example.com, email2@example.com",
            "createAlertModalTelegramNicknamesLabel": "Telegram ники",
            "createAlertModalTelegramNicknamesPlaceholder": "@username1, @username2",
            "createAlertModalIncludeGraphLabel": "Включить график в уведомление",
            "createAlertModalMessageLabel": "Сообщение",
            "createAlertModalSaveButton": "Сохранить",
            "createAlertModalDeleteButton": "Удалить",
            "createAlertModalCreateButton": "Создать",
            "createAlertModalResetButton": "Сбросить",
            "createAlertModalCancelButton": "Отмена"
        },
        "newForecast": {
            "steps": {
                "selectData": "Выбор данных",
                "chooseXy": "Выбор X и Y",
                "chooseTime": "Выбор времени"
            },
            "selectRangeLabel": "Выберите диапазон прогноза",
            "controlledPickerLabel": "Выберите конечную дату",
            "allStepsCompleted": "Все шаги завершены - вы закончили",
            "resetButton": "Сбросить",
            "downloadButton": "Скачать",
            "backButton": "Назад",
            "nextButton": "Далее",
            "stepCompletedMessage": "Шаг {{stepNumber}} уже завершен",
            "completeStepButton": "Завершить шаг",
            "sendButton": "Отправить",
            "currentStepMessage": "Текущий шаг: {{stepNumber}}",
            "selectDataDescription": "Выберите предпочтительный источник данных",
            "loadDataDescription": "Загрузить данные",
            "selectXAxisDescription": "Выберите ось X",
            "selectYAxisDescription": "Выберите ось Y",
            "selectForecastDateDescription": "Выберите дату прогноза",
            "sendButtonDescription": "Если все верно, нажмите кнопку \"отправить\"",
            "loading": "Загрузка...",
            "errorGeneratingForecast": "Ошибка генерации прогноза",
            "exampleCsv": "Пример CSV",
            "exampleJson": "Пример JSON",
            "csv": "CSV",
            "json": "JSON",
            "xlsx": "XLSX"
        }
    }
}
